auto1_etl_challenge/__init__.py
auto1_etl_challenge/constants.py
auto1_etl_challenge/etl.py
auto1_etl_challenge/transformation_errors.py
auto1_etl_challenge/utils.py
auto1_etl_challenge-1.1.0.dist-info/LICENSE
auto1_etl_challenge-1.1.0.dist-info/METADATA
auto1_etl_challenge-1.1.0.dist-info/WHEEL
auto1_etl_challenge-1.1.0.dist-info/top_level.txt
auto1_etl_challenge-1.1.0.dist-info/RECORD
