Metadata-Version: 2.1
Name: auto1-etl-challenge
Version: 1.1.0
Summary: Auto1 ETL Challenge
Home-page: UNKNOWN
Author: Muhammad Aqib
Author-email: <inbox.aqib@gmail.com>
License: UNKNOWN
Keywords: auto1,challenge_me,etl pipeline
Platform: UNKNOWN
Classifier: Development Status :: 5 - Production/Stable
Classifier: Intended Audience :: Developers
Classifier: Programming Language :: Python :: 3
Classifier: Operating System :: Unix
Classifier: Operating System :: MacOS :: MacOS X
Classifier: Operating System :: Microsoft :: Windows
